true/__init__.py
true/collections.py
true/demos/__init__.py
true/demos/collections/01_basic_file_operations.py
true/demos/collections/02_directory_operations.py
true/demos/collections/03_file_creators.py
true/demos/collections/04_os_utils.py
true/demos/collections/README.md
true/demos/enum_registry/01_basic_usage.py
true/demos/enum_registry/02_operations.py
true/demos/enum_registry/03_advanced_features.py
true/demos/enum_registry/README.md
true/demos/enums_toolkits/01_basic_enums.py
true/demos/enums_toolkits/02_metadata_and_serialization.py
true/demos/enums_toolkits/03_dynamic_enums.py
true/demos/enums_toolkits/04_iterable_enums.py
true/demos/enums_toolkits/05_serialization.py
true/demos/enums_toolkits/__init__.py
true/demos/enums_toolkits/README.md
true/demos/time/01_basic_usage.py
true/demos/time/02_time_operations.py
true/demos/time/03_scheduling.py
true/demos/time/04_performance_tools.py
true/demos/time/README.md
true/enum_registry.py
true/enums_toolkits.py
true/exceptions.py
true/re.py
true/time.py
true/toolkits.py
true/types.py
true_core-0.1.3.dist-info/LICENSE.txt
true_core-0.1.3.dist-info/METADATA
true_core-0.1.3.dist-info/WHEEL
true_core-0.1.3.dist-info/RECORD
