Metadata-Version: 2.1
Name: true-core
Version: 0.1.3
Summary: A boilerplate utility package
Home-page: https://github.com/alaamer12/true-core
License: MIT
Keywords: utilities,boilerplate,core
Author: alaamer12
Author-email: ahmedmuhmmed239@gmail.com
Requires-Python: >=3.11,<4.0
Classifier: Development Status :: 4 - Beta
Classifier: Intended Audience :: Developers
Classifier: License :: OSI Approved :: MIT License
Classifier: Programming Language :: Python :: 3
Classifier: Programming Language :: Python :: 3.11
Classifier: Programming Language :: Python :: 3.12
Classifier: Programming Language :: Python :: 3.13
Classifier: Topic :: Software Development :: Libraries :: Python Modules
Provides-Extra: dev
Provides-Extra: docs
Provides-Extra: extreme
Provides-Extra: observer
Provides-Extra: ulid
Requires-Dist: moviepy (>=1.0.3,<1.1.0)
Requires-Dist: pillow (>=9.5.0,<9.6.0)
Requires-Dist: psutil (>=6.1.0,<6.2.0)
Requires-Dist: pydub (>=0.25.1,<0.26.0)
Requires-Dist: pytz (>=2022.7.1,<2022.8.0)
Requires-Dist: uuid-utils (>=0.9.0,<0.10.0) ; extra == "ulid"
Requires-Dist: watchdog (>=6.0.0,<6.1.0) ; extra == "observer"
Project-URL: Documentation, https://true-core.readthedocs.io/en/latest/
Project-URL: Repository, https://github.com/alaamer12/true-core
